{"trigonometry-mcq-questions-NaradAI-Quiz-13": {"1": {"1": "sin(A)", "2": "cos(A)", "3": "tan(A)", "4": "cot(A)", "Q": "What is the reciprocal of cosec(A)?", "ans": "sin(A)"}, "2": {"1": "1", "2": "0", "3": "Undefined", "4": "2", "Q": "What is the value of tan(90\u00b0)?", "ans": "Undefined"}, "3": {"1": "opposite/hypotenuse", "2": "adjacent/hypotenuse", "3": "opposite/adjacent", "4": "hypotenuse/opposite", "Q": "What is the formula for sin(\u03b8) in a right triangle?", "ans": "opposite/hypotenuse"}, "4": {"1": "0 and 1", "2": "-1 and 1", "3": "0 and -1", "4": "1 and 2", "Q": "What is the range of values for the cosine function?", "ans": "-1 and 1"}, "5": {"1": "1", "2": "2", "3": "3", "4": "0", "Q": "What is the value of sin<sup>2</sup>(\u03b8) + cos<sup>2</sup>(\u03b8)?", "ans": "1"}, "all": 5, "title": "Trigonometry MCQ", "subject": "Math", "seo_keywords": ["trigonometry", "mcq", "math", "questions"], "url": "trigonometry-mcq-questions-NaradAI-Quiz-13", "description": "Trigonometry Multiple Choice Questions."}}